skysim/__init__.py
skysim-1.0.2.dist-info/METADATA
skysim-1.0.2.dist-info/WHEEL
skysim-1.0.2.dist-info/top_level.txt
skysim-1.0.2.dist-info/RECORD
