Metadata-Version: 2.1
Name: skysim
Version: 1.0.2
Summary: Python Implementation of skysimAPI
Author: Intel#1563
Requires-Dist: requests
